autouri/__init__.py
autouri/__main__.py
autouri/abspath.py
autouri/autouri.py
autouri/cli.py
autouri/gcsuri.py
autouri/httpurl.py
autouri/loc_aux.py
autouri/metadata.py
autouri/ntp_now.py
autouri/s3uri.py
autouri-0.4.4.data/scripts/autouri
tests/__init__.py
tests/conftest.py
tests/files.py
tests/test_abspath.py
tests/test_autouri_localize.py
tests/test_autouri_lock.py
tests/test_gcsuri.py
tests/test_httpurl.py
tests/test_metadata.py
tests/test_ntp_now.py
tests/test_race_cond.py
tests/test_s3uri.py
autouri-0.4.4.dist-info/LICENSE
autouri-0.4.4.dist-info/METADATA
autouri-0.4.4.dist-info/WHEEL
autouri-0.4.4.dist-info/top_level.txt
autouri-0.4.4.dist-info/RECORD
