Metadata-Version: 2.1
Name: autouri
Version: 0.4.4
Summary: Automatic localization for various URIs (s3://, gs://, http://, https:// and local path)
Home-page: https://github.com/ENCODE-DCC/autouri
Author: Jin wook Lee
Author-email: leepc12@gmail.com
Classifier: Programming Language :: Python :: 3
Classifier: License :: OSI Approved :: MIT License
Classifier: Operating System :: POSIX :: Linux
Requires-Python: >=3.6
License-File: LICENSE
Requires-Dist: requests
Requires-Dist: pyopenssl
Requires-Dist: google-cloud-storage
Requires-Dist: boto3
Requires-Dist: awscli
Requires-Dist: dateparser
Requires-Dist: filelock (>=3.12.0)
Requires-Dist: six (>=1.13.0)
Requires-Dist: ntplib
